{
  "profile_summary": {
    "time_budget": 180,
    "num_target_galleries": 28,
    "total_stops": 57
  },
  "route": [
    {
      "gallery": 200,
      "name": "Chinese Ceramics & More!",
      "region": "chinese_ceramics",
      "is_target": false,
      "time_estimate_min": 2,
      "object_count": 52,
      "featured_artworks": [
        {
          "object_id": 42229,
          "title": "Vase",
          "culture": "China",
          "date": "1713\u201322",
          "classification": "Ceramics",
          "medium": "Porcelain with peach-bloom glaze (Jingdezhen ware)\r\n\r\n",
          "alt_text": "Slender porcelain vase with a white rim, three neck rings, and mottled reddish-pink glaze",
          "image_url": "https://images.metmuseum.org/CRDImages/as/mobile-large/DP246426.jpg",
          "highlight": true,
          "score": 0.58,
          "tag": "affinity"
        }
      ],
      "lat": 40.779262161,
      "lng": -73.963184305,
      "neighbors": [
        201,
        202
      ]
    },
    {
      "gallery": 202,
      "name": "Gallery 202",
      "region": "chinese_ceramics",
      "is_target": true,
      "time_estimate_min": 5,
      "object_count": 10,
      "featured_artworks": [
        {
          "object_id": 39666,
          "title": "Jar with dragon",
          "culture": "China",
          "date": "early 15th century",
          "classification": "Ceramics",
          "medium": "Porcelain painted with cobalt blue under transparent glaze (Jingdezhen ware)\r\n\r\n",
          "alt_text": "Porcelain jar decorated with a blue underglaze dragon among clouds and a band of lotus petals",
          "image_url": "https://images.metmuseum.org/CRDImages/as/mobile-large/DP-32251-001.jpg",
          "highlight": true,
          "score": 0.58,
          "tag": "affinity"
        },
        {
          "object_id": 45515,
          "title": "One from set of five squared food vessels (muk\u014dzuke) for tea-gathering meal",
          "culture": "Japan",
          "date": "early 17th century",
          "classification": "Ceramics",
          "medium": "Stoneware with iron-oxide and copper green overglaze decoration (Mino ware, Yashichida Oribe type)\r\n",
          "alt_text": "Squared stoneware vessel with a cream glaze featuring a dark hook-like motif and a diagonal lattice pattern",
          "image_url": "https://images.metmuseum.org/CRDImages/as/mobile-large/LC-1973_80_2-001.jpg",
          "highlight": false,
          "score": 0.48,
          "tag": "stretch"
        },
        {
          "object_id": 42193,
          "title": "Incense burner",
          "culture": "China",
          "date": "dated 1512",
          "classification": "Ceramics",
          "medium": "Stoneware with relief decoration under colored glazes",
          "alt_text": "Ornate stoneware incense burner with green and amber glazes, dragons, flowers, and a carved wooden lid",
          "image_url": "https://images.metmuseum.org/CRDImages/as/mobile-large/DP-32252-001.jpg",
          "highlight": false,
          "score": 0.48,
          "tag": "wildcard"
        }
      ],
      "lat": 40.779239302,
      "lng": -73.962979541,
      "neighbors": [
        200,
        203,
        204,
        207
      ]
    },
    {
      "gallery": 207,
      "name": "Chinese Art: Ancient to Tang Dynasty",
      "region": "chinese_ancient",
      "is_target": true,
      "time_estimate_min": 5,
      "object_count": 247,
      "featured_artworks": [
        {
          "object_id": 42183,
          "title": "Dish in the shape of a leaf",
          "culture": "China",
          "date": "late 7th\u2013early 8th century",
          "classification": "Metalwork",
          "medium": "Silver with parcel gilding",
          "alt_text": "Silver leaf-shaped dish with interior motifs of birds and flowers within spiraling stem circles",
          "image_url": "https://images.metmuseum.org/CRDImages/as/mobile-large/DP100673.jpg",
          "highlight": true,
          "score": 0.58,
          "tag": "affinity"
        },
        {
          "object_id": 64920,
          "title": "Ornamental Plaque",
          "culture": "China",
          "date": "4th\u20135th century",
          "classification": "Metalwork",
          "medium": "Gilt bronze, gold, lapis lazuli, turquoise, and white coral",
          "alt_text": "Five-sided gold ornamental plaque with intricate filigree and multicolored crescent-shaped stone inlays",
          "image_url": "https://images.metmuseum.org/CRDImages/as/mobile-large/DP290762.jpg",
          "highlight": false,
          "score": 0.48,
          "tag": "stretch"
        },
        {
          "object_id": 65100,
          "title": "Standing attendant",
          "culture": "China",
          "date": "7th century",
          "classification": "Sculpture",
          "medium": "Earthenware with pigment",
          "alt_text": "Earthenware sculpture of a standing person with clasped hands wearing a green tunic and boots",
          "image_url": "https://images.metmuseum.org/CRDImages/as/mobile-large/2002_501.JPG",
          "highlight": false,
          "score": 0.48,
          "tag": "wildcard"
        }
      ],
      "lat": 40.77945,
      "lng": -73.96285,
      "neighbors": [
        202,
        206,
        208,
        219,
        220
      ]
    },
    {
      "gallery": 219,
      "name": "Chinese Jade & Decorative Arts",
      "region": "chinese_ancient",
      "is_target": true,
      "time_estimate_min": 5,
      "object_count": 118,
      "featured_artworks": [
        {
          "object_id": 49349,
          "title": "Brush Washer",
          "culture": "China",
          "date": "",
          "classification": "Ceramics",
          "medium": "Porcelain with peachbloom glaze (Jingdezhen ware)",
          "alt_text": "A low, rounded porcelain brush washer with mottled reddish-pink glaze and a white interior",
          "image_url": "https://images.metmuseum.org/CRDImages/as/mobile-large/DP326725.jpg",
          "highlight": false,
          "score": 0.48,
          "tag": "affinity"
        },
        {
          "object_id": 50714,
          "title": "Vase in the shape of an ancient ritual beaker (gu)",
          "culture": "China",
          "date": "early 20th century",
          "classification": "Ceramics",
          "medium": "Porcelain with a pale green glaze (Jingdezhen ware)",
          "alt_text": "Light-toned porcelain vase with a wide flared rim and a bulbous central section",
          "image_url": "https://images.metmuseum.org/CRDImages/as/mobile-large/66_206_9.jpg",
          "highlight": false,
          "score": 0.48,
          "tag": "stretch"
        },
        {
          "object_id": 50995,
          "title": "Water coupe",
          "culture": "China",
          "date": "",
          "classification": "Ceramics",
          "medium": "Porcelain with peach-bloom glaze (Jingdezhen ware)",
          "alt_text": "Dome-shaped porcelain vessel with a small flared neck and a circular medallion of swirling patterns",
          "image_url": "https://images.metmuseum.org/CRDImages/as/mobile-large/76014.jpg",
          "highlight": false,
          "score": 0.48,
          "tag": "wildcard"
        }
      ],
      "lat": 40.77935,
      "lng": -73.96255,
      "neighbors": [
        207,
        220,
        222
      ]
    },
    {
      "gallery": 220,
      "name": "Chinese Decorative Arts",
      "region": "chinese_ancient",
      "is_target": true,
      "time_estimate_min": 5,
      "object_count": 49,
      "featured_artworks": [
        {
          "object_id": 856282,
          "title": "Table screen with landscape",
          "culture": "China",
          "date": "second half 15th century",
          "classification": "Cloisonn\u00e9",
          "medium": "Cloisonn\u00e9 enamel, wood frame and stand",
          "alt_text": "Horizontal table screen with a cloisonn\u00e9 enamel landscape in a carved dark wood frame and stand",
          "image_url": "https://images.metmuseum.org/CRDImages/as/mobile-large/DP-24553-001.jpg",
          "highlight": true,
          "score": 0.58,
          "tag": "affinity"
        },
        {
          "object_id": 46915,
          "title": "Vase",
          "culture": "China",
          "date": "",
          "classification": "Ceramics",
          "medium": "Porcelain painted in underglaze cobalt blue and overglaze polychrome enamels (Jingdezhen ware)",
          "alt_text": "Porcelain vase with a flared rim and base, decorated with colorful floral and geometric vertical panels",
          "image_url": "https://images.metmuseum.org/CRDImages/as/mobile-large/79_2_1375_S1_sf.jpg",
          "highlight": false,
          "score": 0.48,
          "tag": "stretch"
        },
        {
          "object_id": 48559,
          "title": "Gourd-shaped vase with gourds on vines and bats",
          "culture": "China",
          "date": "early 18th century",
          "classification": "Ceramics",
          "medium": "Porcelain painted in underglaze cobalt blue (Jingdezhen ware)\r\n",
          "alt_text": "A white porcelain double-gourd vase decorated with blue underglaze scrolling vines, small gourd fruits, and bats",
          "image_url": "https://images.metmuseum.org/CRDImages/as/mobile-large/DP264293.jpg",
          "highlight": false,
          "score": 0.48,
          "tag": "wildcard"
        }
      ],
      "lat": 40.7795,
      "lng": -73.9625,
      "neighbors": [
        207,
        219,
        221
      ]
    },
    {
      "gallery": 207,
      "name": "Chinese Art: Ancient to Tang Dynasty",
      "region": "chinese_ancient",
      "is_target": true,
      "time_estimate_min": 1,
      "object_count": 247,
      "featured_artworks": [],
      "lat": 40.77945,
      "lng": -73.96285,
      "neighbors": [
        202,
        206,
        208,
        219,
        220
      ]
    },
    {
      "gallery": 208,
      "name": "Chinese Buddhist Art ",
      "region": "chinese_buddhist",
      "is_target": false,
      "time_estimate_min": 2,
      "object_count": 20,
      "featured_artworks": [
        {
          "object_id": 42163,
          "title": "Buddha, probably Amitabha",
          "culture": "China",
          "date": "early 7th century",
          "classification": "Sculpture",
          "medium": "Dry lacquer with polychrome pigment and gilding",
          "alt_text": "Seated sculpture of a person with missing hands wearing a robe with red and green patterns",
          "image_url": "https://images.metmuseum.org/CRDImages/as/mobile-large/DP-15581-004.jpg",
          "highlight": true,
          "score": 0.58,
          "tag": "affinity"
        }
      ],
      "lat": 40.779721287,
      "lng": -73.962478484,
      "neighbors": [
        207,
        209,
        233
      ]
    },
    {
      "gallery": 209,
      "name": "Chinese Buddhist Art",
      "region": "chinese_buddhist",
      "is_target": false,
      "time_estimate_min": 2,
      "object_count": 7,
      "featured_artworks": [
        {
          "object_id": 42721,
          "title": "Rock in the form of a fantastic mountain",
          "culture": "China",
          "date": "20th century",
          "classification": "Sculpture",
          "medium": "Taihu limestone; wood stand",
          "alt_text": "A vertical light-colored porous rock with many holes resting on an intricately carved dark base",
          "image_url": "https://images.metmuseum.org/CRDImages/as/mobile-large/2011_575_1ab.jpg",
          "highlight": false,
          "score": 0.48,
          "tag": "affinity"
        }
      ],
      "lat": 40.77985,
      "lng": -73.9624,
      "neighbors": [
        208,
        239
      ]
    },
    {
      "gallery": 239,
      "name": "South Asian Hindu-Buddhist and Jain Sculpture",
      "region": "south_asian",
      "is_target": false,
      "time_estimate_min": 2,
      "object_count": 2,
      "featured_artworks": [
        {
          "object_id": 38133,
          "title": "Enthroned Vishnu",
          "culture": "India",
          "date": "second half of the 8th\u2013early 9th century",
          "classification": "Sculpture",
          "medium": "Granulite",
          "alt_text": "Vertical stone sculpture of a four-armed person seated on a throne in a relaxed posture",
          "image_url": "https://images.metmuseum.org/CRDImages/as/mobile-large/DT5240.jpg",
          "highlight": true,
          "score": 0.58,
          "tag": "affinity"
        }
      ],
      "lat": 40.779898381,
      "lng": -73.962193753,
      "neighbors": [
        209,
        238,
        240,
        241
      ]
    },
    {
      "gallery": 241,
      "name": "Indian Medieval Sculpture Gallery",
      "region": "south_asian",
      "is_target": false,
      "time_estimate_min": 2,
      "object_count": 11,
      "featured_artworks": [
        {
          "object_id": 38146,
          "title": "Vishnu",
          "culture": "India (Punjab)",
          "date": "10th\u201311th century",
          "classification": "Sculpture",
          "medium": "Sandstone",
          "alt_text": "Vertical sandstone relief sculpture of a four-armed figure surrounded by smaller figures and decorative carvings",
          "image_url": "https://images.metmuseum.org/CRDImages/as/mobile-large/DT5052.jpg",
          "highlight": true,
          "score": 0.58,
          "tag": "affinity"
        }
      ],
      "lat": 40.779923533,
      "lng": -73.962067714,
      "neighbors": [
        239,
        240,
        242,
        243,
        244
      ]
    },
    {
      "gallery": 244,
      "name": "Southeast Asian Art",
      "region": "southeast_asian",
      "is_target": true,
      "time_estimate_min": 5,
      "object_count": 69,
      "featured_artworks": [
        {
          "object_id": 37743,
          "title": "Ceremonial Object in the Shape of an Ax",
          "culture": "Indonesia, possibly Sulawesi",
          "date": "ca. 100 BCE\u2013300 CE",
          "classification": "Metalwork",
          "medium": "Bronze alloy",
          "alt_text": "Vertical bronze object shaped like an ax with a ridged neck and green patina",
          "image_url": "https://images.metmuseum.org/CRDImages/as/mobile-large/DP221496.jpg",
          "highlight": true,
          "score": 0.58,
          "tag": "affinity"
        },
        {
          "object_id": 37747,
          "title": "Box for Betel Leaves",
          "culture": "Indonesia (Sulawesi)",
          "date": "ca. 500 BCE\u2013300 CE",
          "classification": "Metalwork",
          "medium": "Bronze",
          "alt_text": "Rectangular green-patinated bronze box with a tiered lid featuring parallel bars, small figures, and geometric patterns",
          "image_url": "https://images.metmuseum.org/CRDImages/as/mobile-large/DP228215.jpg",
          "highlight": true,
          "score": 0.58,
          "tag": "stretch"
        },
        {
          "object_id": 51937,
          "title": "Portions of a Buckle",
          "culture": "Vietnam",
          "date": "500 BCE\u2013300 CE",
          "classification": "Metalwork",
          "medium": "Bronze",
          "alt_text": "Two bronze buckle portions with stylized bird figures and spiral designs in dark greenish-grey",
          "image_url": "https://images.metmuseum.org/CRDImages/as/mobile-large/2001_433_376ab.jpg",
          "highlight": false,
          "score": 0.48,
          "tag": "wildcard"
        }
      ],
      "lat": 40.779996135,
      "lng": -73.962027516,
      "neighbors": [
        216,
        241,
        243,
        245,
        247
      ]
    },
    {
      "gallery": 245,
      "name": "Southeast Asian Art",
      "region": "southeast_asian",
      "is_target": true,
      "time_estimate_min": 5,
      "object_count": 16,
      "featured_artworks": [
        {
          "object_id": 51170,
          "title": "Standing Avalokiteshvara, the Bodhisattva of Infinite Compassion",
          "culture": "Vietnam",
          "date": "ca. 7th century",
          "classification": "Sculpture",
          "medium": "Gilt bronze",
          "alt_text": "Weathered metal sculpture of a standing figure with a towering headpiece and green oxidation",
          "image_url": "https://images.metmuseum.org/CRDImages/as/mobile-large/DP145420.jpg",
          "highlight": true,
          "score": 0.58,
          "tag": "affinity"
        },
        {
          "object_id": 38158,
          "title": "Shiva",
          "culture": "Vietnam or Southern Cambodia",
          "date": "mid- 7th century",
          "classification": "Sculpture",
          "medium": "Sandstone",
          "alt_text": "Vertical sandstone sculpture of a person with a tall hair arrangement and a simple waistcloth",
          "image_url": "https://images.metmuseum.org/CRDImages/as/mobile-large/LK.1987.17_DP310113R1_25W.jpg",
          "highlight": true,
          "score": 0.58,
          "tag": "stretch"
        },
        {
          "object_id": 38159,
          "title": "Standing Ganesha",
          "culture": "Cambodia",
          "date": "second half 7th century",
          "classification": "Sculpture",
          "medium": "Stone",
          "alt_text": "Stone sculpture of a standing figure with an elephant head and broken limbs",
          "image_url": "https://images.metmuseum.org/CRDImages/as/mobile-large/DT7384.jpg",
          "highlight": true,
          "score": 0.58,
          "tag": "wildcard"
        }
      ],
      "lat": 40.780049147,
      "lng": -73.961988858,
      "neighbors": [
        244,
        246,
        247,
        252,
        253
      ]
    },
    {
      "gallery": 246,
      "name": "Southeast Asian Art",
      "region": "southeast_asian",
      "is_target": false,
      "time_estimate_min": 2,
      "object_count": 28,
      "featured_artworks": [
        {
          "object_id": 38954,
          "title": "Standing Buddha",
          "culture": "Thailand (Nakhon Pathom Province)",
          "date": "8th\u20139th century",
          "classification": "Sculpture",
          "medium": "Bronze with traces of gilt",
          "alt_text": "Bronze sculpture of a standing figure with raised hands and a textured head",
          "image_url": "https://images.metmuseum.org/CRDImages/as/mobile-large/DP310136.jpg",
          "highlight": true,
          "score": 0.58,
          "tag": "affinity"
        }
      ],
      "lat": 40.780109477,
      "lng": -73.961944863,
      "neighbors": [
        215,
        245,
        248
      ]
    },
    {
      "gallery": 248,
      "name": "Southeast Asian Art",
      "region": "southeast_asian",
      "is_target": true,
      "time_estimate_min": 5,
      "object_count": 8,
      "featured_artworks": [
        {
          "object_id": 37434,
          "title": "Bottle",
          "culture": "Thailand (Buriram Province)",
          "date": "early 12th century",
          "classification": "Ceramics",
          "medium": "Stoneware",
          "alt_text": "Dark stoneware bottle with a globular body, long neck, and incised vertical lines",
          "image_url": "https://images.metmuseum.org/CRDImages/as/mobile-large/264795_botl.jpg",
          "highlight": false,
          "score": 0.48,
          "tag": "affinity"
        },
        {
          "object_id": 37436,
          "title": "Covered Lime Pot in the Form of a Rabbit",
          "culture": "Thailand",
          "date": "second half of the 12th century",
          "classification": "Ceramics",
          "medium": "Stoneware",
          "alt_text": "Dark stoneware vessel shaped like a long-eared animal with incised decorative patterns and a tiered lid",
          "image_url": "https://images.metmuseum.org/CRDImages/as/mobile-large/1986_506_3ab_O1.jpg",
          "highlight": false,
          "score": 0.48,
          "tag": "stretch"
        },
        {
          "object_id": 37439,
          "title": "Covered Cylinderical Jar",
          "culture": "Thailand (Buriram Province)",
          "date": "11th century",
          "classification": "Ceramics",
          "medium": "Stoneware",
          "alt_text": "Small dark stoneware jar with a tiered conical lid and a flared base",
          "image_url": "https://images.metmuseum.org/CRDImages/as/mobile-large/1986_506_10ab.jpg",
          "highlight": false,
          "score": 0.48,
          "tag": "wildcard"
        }
      ],
      "lat": 40.780137591,
      "lng": -73.96188656,
      "neighbors": [
        246,
        249
      ]
    },
    {
      "gallery": 249,
      "name": "Southeast Asian Art",
      "region": "southeast_asian",
      "is_target": true,
      "time_estimate_min": 5,
      "object_count": 25,
      "featured_artworks": [
        {
          "object_id": 65095,
          "title": "Antefix with Kneeling Guardian",
          "culture": "Cambodia",
          "date": "third quarter of the 10th century",
          "classification": "Sculpture",
          "medium": "Reddish sandstone",
          "alt_text": "Reddish-brown stone sculpture of a seated person with an ornate headdress and swirling scroll backdrop",
          "image_url": "https://images.metmuseum.org/CRDImages/as/mobile-large/2003.142.jpg",
          "highlight": true,
          "score": 0.58,
          "tag": "affinity"
        },
        {
          "object_id": 38265,
          "title": "Brahma",
          "culture": "Cambodia",
          "date": "first quarter of the 10th century",
          "classification": "Sculpture",
          "medium": "Sandstone",
          "alt_text": "Sandstone sculpture of a three-headed, four-armed figure wearing an ornate crown and pleated garment",
          "image_url": "https://images.metmuseum.org/CRDImages/as/mobile-large/DT5227.jpg",
          "highlight": true,
          "score": 0.58,
          "tag": "stretch"
        },
        {
          "object_id": 38905,
          "title": "Head of Shiva (lingakosha)",
          "culture": "Vietnam (Champa, probably Quang Nam Province)",
          "date": "late 9th\u201310th century",
          "classification": "Sculpture",
          "medium": "Gold and silver repouss\u00e9",
          "alt_text": "A metal sculpture of a head with a third eye, a moustache, and a tiered topknot",
          "image_url": "https://images.metmuseum.org/CRDImages/as/mobile-large/DP291638.jpg",
          "highlight": true,
          "score": 0.58,
          "tag": "wildcard"
        }
      ],
      "lat": 40.780199747,
      "lng": -73.961833947,
      "neighbors": [
        248,
        250
      ]
    },
    {
      "gallery": 250,
      "name": "Southeast Asian Art",
      "region": "southeast_asian",
      "is_target": true,
      "time_estimate_min": 5,
      "object_count": 44,
      "featured_artworks": [
        {
          "object_id": 63532,
          "title": "Seated Buddha",
          "culture": "Thailand",
          "date": "15th century",
          "classification": "Sculpture",
          "medium": "Bronze",
          "alt_text": "Bronze sculpture of a seated person with elongated earlobes and a flame-shaped head protrusion",
          "image_url": "https://images.metmuseum.org/CRDImages/as/mobile-large/DP-15581-052.jpg",
          "highlight": true,
          "score": 0.58,
          "tag": "affinity"
        },
        {
          "object_id": 38318,
          "title": "Crowned Buddha",
          "culture": "Burma",
          "date": "ca. 13th\u2013early 14th century",
          "classification": "Sculpture",
          "medium": "Wood with lacquer and gilt",
          "alt_text": "Standing wooden sculpture of a person wearing an elaborate tall crown and thin, fitted robes",
          "image_url": "https://images.metmuseum.org/CRDImages/as/mobile-large/1986_207.jpg",
          "highlight": true,
          "score": 0.58,
          "tag": "stretch"
        },
        {
          "object_id": 39107,
          "title": "Seated Buddha",
          "culture": "Thailand",
          "date": "first half of the 13th century",
          "classification": "Sculpture",
          "medium": "Bronze",
          "alt_text": "Bronze sculpture of a seated person with an ornate mandorla on a multi-tiered pedestal",
          "image_url": "https://images.metmuseum.org/CRDImages/as/mobile-large/1980_526_1_224099.JPG",
          "highlight": true,
          "score": 0.58,
          "tag": "wildcard"
        }
      ],
      "lat": 40.78027289,
      "lng": -73.961787896,
      "neighbors": [
        249
      ]
    },
    {
      "gallery": 249,
      "name": "Southeast Asian Art",
      "region": "southeast_asian",
      "is_target": true,
      "time_estimate_min": 1,
      "object_count": 25,
      "featured_artworks": [],
      "lat": 40.780199747,
      "lng": -73.961833947,
      "neighbors": [
        248,
        250
      ]
    },
    {
      "gallery": 248,
      "name": "Southeast Asian Art",
      "region": "southeast_asian",
      "is_target": true,
      "time_estimate_min": 1,
      "object_count": 8,
      "featured_artworks": [],
      "lat": 40.780137591,
      "lng": -73.96188656,
      "neighbors": [
        246,
        249
      ]
    },
    {
      "gallery": 246,
      "name": "Southeast Asian Art",
      "region": "southeast_asian",
      "is_target": false,
      "time_estimate_min": 1,
      "object_count": 28,
      "featured_artworks": [],
      "lat": 40.780109477,
      "lng": -73.961944863,
      "neighbors": [
        215,
        245,
        248
      ]
    },
    {
      "gallery": 245,
      "name": "Southeast Asian Art",
      "region": "southeast_asian",
      "is_target": true,
      "time_estimate_min": 1,
      "object_count": 16,
      "featured_artworks": [],
      "lat": 40.780049147,
      "lng": -73.961988858,
      "neighbors": [
        244,
        246,
        247,
        252,
        253
      ]
    },
    {
      "gallery": 247,
      "name": "Southeast Asian Art",
      "region": "southeast_asian",
      "is_target": true,
      "time_estimate_min": 5,
      "object_count": 90,
      "featured_artworks": [
        {
          "object_id": 39020,
          "title": "Seated Transcendent Buddha Vairochana",
          "culture": "Indonesia (Java)",
          "date": "ca. late 9th century",
          "classification": "Sculpture",
          "medium": "Bronze",
          "alt_text": "Bronze sculpture of a figure with a halo seated in a meditative pose on a lotus base",
          "image_url": "https://images.metmuseum.org/CRDImages/as/mobile-large/DT5232.jpg",
          "highlight": true,
          "score": 0.58,
          "tag": "affinity"
        },
        {
          "object_id": 39021,
          "title": "The Transcendent Buddha Vairochana (?) Seated in Western Fashion",
          "culture": "Indonesia (Java)",
          "date": "9th century",
          "classification": "Sculpture",
          "medium": "Bronze",
          "alt_text": "Green bronze sculpture of a person seated on a throne supported by two stylized animals",
          "image_url": "https://images.metmuseum.org/CRDImages/as/mobile-large/DT8665.jpg",
          "highlight": true,
          "score": 0.58,
          "tag": "stretch"
        },
        {
          "object_id": 38994,
          "title": "Buddha Attended by Bodhisattvas Avalokiteshvara and Maitreya",
          "culture": "Sumatra or southern Thailand",
          "date": "second half of the 8th century",
          "classification": "Sculpture",
          "medium": "Copper alloy",
          "alt_text": "Copper alloy sculpture of three figures standing on lotus pedestals atop a rectangular base",
          "image_url": "https://images.metmuseum.org/CRDImages/as/mobile-large/LK.1984.386.4_DP303951R1_25U.jpg",
          "highlight": true,
          "score": 0.58,
          "tag": "wildcard"
        }
      ],
      "lat": 40.78003077,
      "lng": -73.961922535,
      "neighbors": [
        244,
        245,
        252
      ]
    },
    {
      "gallery": 252,
      "name": "Arts of Tibet and Nepal",
      "region": "himalayan",
      "is_target": true,
      "time_estimate_min": 5,
      "object_count": 34,
      "featured_artworks": [
        {
          "object_id": 50799,
          "title": "Tara, the Buddhist Savior",
          "culture": "Nepal, Kathmandu Valley",
          "date": "14th century",
          "classification": "Sculpture",
          "medium": "Gilt copper alloy with color and semiprecious stone inlay",
          "alt_text": "Gilded metal sculpture of a standing woman wearing a tall crown and holding a flower",
          "image_url": "https://images.metmuseum.org/CRDImages/as/mobile-large/DT5221.jpg",
          "highlight": true,
          "score": 0.58,
          "tag": "affinity"
        },
        {
          "object_id": 38327,
          "title": "Bodhisattva, probably Padmapani Lokeshvara",
          "culture": "Nepal (Kathmandu Valley)",
          "date": "10th\u201311th century",
          "classification": "Sculpture",
          "medium": "Gilt copper alloy",
          "alt_text": "A gold-toned metal sculpture of a standing figure wearing an ornate crown and holding a flowering vine",
          "image_url": "https://images.metmuseum.org/CRDImages/as/mobile-large/DP102266.jpg",
          "highlight": true,
          "score": 0.58,
          "tag": "stretch"
        },
        {
          "object_id": 38328,
          "title": "The Bodhisattva Maitreya, the Buddha of the Future",
          "culture": "Nepal",
          "date": "11th century",
          "classification": "Sculpture",
          "medium": "Copper alloy with gilding and color",
          "alt_text": "Gilded metal statue of a slender standing person with an ornate crown and jewelry",
          "image_url": "https://images.metmuseum.org/CRDImages/as/mobile-large/DP-30183-001.jpg",
          "highlight": true,
          "score": 0.58,
          "tag": "wildcard"
        }
      ],
      "lat": 40.780052854,
      "lng": -73.96190643,
      "neighbors": [
        245,
        247,
        253
      ]
    },
    {
      "gallery": 253,
      "name": "Arts of Tibet and Nepal",
      "region": "himalayan",
      "is_target": true,
      "time_estimate_min": 5,
      "object_count": 34,
      "featured_artworks": [
        {
          "object_id": 38332,
          "title": "Seated Avalokiteshvara, the Buddha of Infinite Compassion",
          "culture": "Tibet or Mongolia",
          "date": "17th century",
          "classification": "Sculpture",
          "medium": "Gilt copper alloy",
          "alt_text": "Gilt copper alloy sculpture of a seated person with a tall crown on a lotus pedestal",
          "image_url": "https://images.metmuseum.org/CRDImages/as/mobile-large/DP170265.jpg",
          "highlight": true,
          "score": 0.58,
          "tag": "affinity"
        },
        {
          "object_id": 38582,
          "title": "Twenty-One Emanations of the Goddess Tara",
          "culture": "Tibet",
          "date": "14th century",
          "classification": "Sculpture",
          "medium": "Stone with polychrome",
          "alt_text": "Carved stone stele with a central seated figure surrounded by twenty-one smaller figures on a red background",
          "image_url": "https://images.metmuseum.org/CRDImages/as/mobile-large/DP252972.jpg",
          "highlight": true,
          "score": 0.58,
          "tag": "stretch"
        },
        {
          "object_id": 78191,
          "title": "Buddha Shakyamuni",
          "culture": "Central Tibet",
          "date": "12th century",
          "classification": "Sculpture",
          "medium": "Brass with colored pigments",
          "alt_text": "Seated brass sculpture of a person with blue textured hair in a cross-legged pose with downcast eyes",
          "image_url": "https://images.metmuseum.org/CRDImages/as/mobile-large/DP-15581-015.jpg",
          "highlight": true,
          "score": 0.58,
          "tag": "wildcard"
        }
      ],
      "lat": 40.780064764,
      "lng": -73.961979045,
      "neighbors": [
        216,
        245,
        252
      ]
    },
    {
      "gallery": 216,
      "name": " Chinese Painting and Calligraphy: Selections from the Collection",
      "region": "chinese_painting",
      "is_target": true,
      "time_estimate_min": 5,
      "object_count": 2,
      "featured_artworks": [
        {
          "object_id": 42148,
          "title": "Seated luohan holding a fan",
          "culture": "China",
          "date": "late 18th century",
          "classification": "Jade",
          "medium": "Jade (nephrite)",
          "alt_text": "Vertical stone sculpture of a seated person with a fan inside a craggy rock grotto",
          "image_url": "https://images.metmuseum.org/CRDImages/as/mobile-large/DP350747.jpg",
          "highlight": false,
          "score": 0.48,
          "tag": "affinity"
        },
        {
          "object_id": 36445,
          "title": "Rubbing of Stele for Shi Chen",
          "culture": "China",
          "date": "19th century rubbing; stele dated 169 CE",
          "classification": "Rubbing",
          "medium": "Rubbing mounted in an album of thirty-two leaves; ink on paper",
          "alt_text": "Ink rubbing on paper showing two pages of stylized script in six vertical columns with red seals",
          "image_url": "https://images.metmuseum.org/CRDImages/as/mobile-large/DP363587.jpg",
          "highlight": false,
          "score": 0.39,
          "tag": "stretch"
        }
      ],
      "lat": 40.780057202,
      "lng": -73.962077937,
      "neighbors": [
        215,
        217,
        244,
        253
      ]
    },
    {
      "gallery": 217,
      "name": "Chinese Courtyard in the Style of the Ming Dynasty",
      "region": "chinese_painting",
      "is_target": false,
      "time_estimate_min": 3,
      "object_count": 0,
      "featured_artworks": [],
      "lat": 40.780140228,
      "lng": -73.962198618,
      "neighbors": [
        210,
        216,
        218
      ]
    },
    {
      "gallery": 210,
      "name": " Chinese Painting and Calligraphy: Selections from the Collection",
      "region": "chinese_painting",
      "is_target": true,
      "time_estimate_min": 5,
      "object_count": 28,
      "featured_artworks": [
        {
          "object_id": 40055,
          "title": "Emperor Xuanzong's flight to Shu",
          "culture": "China",
          "date": "mid-12th century",
          "classification": "Paintings",
          "medium": "Hanging scroll; ink, color, and gold on silk",
          "alt_text": "Landscape painting on a scroll featuring about nine people traveling through mountains on horseback and foot",
          "image_url": "https://images.metmuseum.org/CRDImages/as/mobile-large/DP247676.jpg",
          "highlight": true,
          "score": 0.58,
          "tag": "affinity"
        },
        {
          "object_id": 50211,
          "title": "Bottle in meiping shape with \u201ctortoiseshell\u201d glaze",
          "culture": "China",
          "date": "14th century",
          "classification": "Ceramics",
          "medium": "Stoneware with iron glaze (Jizhou ware)\r\n\r\n",
          "alt_text": "High-shouldered pottery bottle with a glossy black glaze and numerous mottled amber and tan patches",
          "image_url": "https://images.metmuseum.org/CRDImages/as/mobile-large/DP-14607-043.jpg",
          "highlight": false,
          "score": 0.48,
          "tag": "stretch"
        },
        {
          "object_id": 52679,
          "title": "Vase",
          "culture": "China",
          "date": "12th\u201313th century",
          "classification": "Ceramics",
          "medium": "Stoneware with crackled celadon glaze (Guan ware)\r\n\r\n",
          "alt_text": "Pale greenish-blue ceramic vase with a network of fine brown crackles and a flared foot",
          "image_url": "https://images.metmuseum.org/CRDImages/as/mobile-large/DP335586.jpg",
          "highlight": false,
          "score": 0.48,
          "tag": "wildcard"
        }
      ],
      "lat": 40.780212407,
      "lng": -73.962252558,
      "neighbors": [
        211,
        217,
        232
      ]
    },
    {
      "gallery": 232,
      "name": "The Infinite Artistry of Japanese Ceramics",
      "region": "japanese",
      "is_target": false,
      "time_estimate_min": 2,
      "object_count": 7,
      "featured_artworks": [
        {
          "object_id": 52284,
          "title": "Dish with Stylized Scrolls and Flowers",
          "culture": "Japan",
          "date": "late 17th\u2013early 18th century",
          "classification": "Ceramics",
          "medium": "Porcelain with cobalt blue under transparent glaze and polychrome enamels over the glaze (Hizen ware, Nabeshima type)",
          "alt_text": "A circular porcelain dish featuring a repeating pattern of eight blue scrolls and eight red flowers",
          "image_url": "https://images.metmuseum.org/CRDImages/as/mobile-large/1975_268_562_O1_sf.jpg",
          "highlight": false,
          "score": 0.48,
          "tag": "affinity"
        }
      ],
      "lat": 40.780169066,
      "lng": -73.962431458,
      "neighbors": [
        210,
        223,
        231
      ]
    },
    {
      "gallery": 231,
      "name": "The Infinite Artistry of Japanese Ceramics",
      "region": "japanese",
      "is_target": true,
      "time_estimate_min": 5,
      "object_count": 76,
      "featured_artworks": [
        {
          "object_id": 45753,
          "title": "Street Scenes in Kyoto",
          "culture": "Japan",
          "date": "late 17th century",
          "classification": "Paintings",
          "medium": "Handscroll; ink and color on paper",
          "alt_text": "Fragment of a handscroll depicting numerous people in colorful robes walking through a town with gold-leaf clouds",
          "image_url": "https://images.metmuseum.org/CRDImages/as/mobile-large/DP233824_CRD.jpg",
          "highlight": false,
          "score": 0.48,
          "tag": "affinity"
        },
        {
          "object_id": 47258,
          "title": "Sake Bottle (Tokkuri) in the Shape of an Eggplant",
          "culture": "Japan",
          "date": "second half 19th century",
          "classification": "Ceramics",
          "medium": "Stoneware with iridescent iron glaze and rice straw ash (Bairin ware)",
          "alt_text": "Eggplant shaped ceramic vessel with dark iridescent glaze and a textured calyx at its narrow neck",
          "image_url": "https://images.metmuseum.org/CRDImages/as/mobile-large/DP-43523-001.jpg",
          "highlight": false,
          "score": 0.48,
          "tag": "stretch"
        },
        {
          "object_id": 63711,
          "title": "Set of Five Soba Cups (Soba Choko) with Swirl Patterns",
          "culture": "Japan",
          "date": "late 18th\u2013early 19th century",
          "classification": "Ceramics",
          "medium": "Porcelain with cobalt blue under transparent glaze (Hizen ware, Arita type)",
          "alt_text": "Five small off-white porcelain cups decorated with vertical rows of hand-painted blue spirals and hooked lines",
          "image_url": "https://images.metmuseum.org/CRDImages/as/mobile-large/LC-1975_268_643-647_003.jpg",
          "highlight": false,
          "score": 0.48,
          "tag": "wildcard"
        }
      ],
      "lat": 40.780222751,
      "lng": -73.962535596,
      "neighbors": [
        224,
        230,
        232
      ]
    },
    {
      "gallery": 230,
      "name": "The Infinite Artistry of Japanese Ceramics",
      "region": "japanese",
      "is_target": false,
      "time_estimate_min": 2,
      "object_count": 25,
      "featured_artworks": [
        {
          "object_id": 63589,
          "title": "Set of Five Small Dishes (Kozara) with Flowering Plum and Warbler",
          "culture": "Japan",
          "date": "ca. 1640s",
          "classification": "Ceramics",
          "medium": "Porcelain with cobalt blue under transparent glaze and iron-brown rim (Hizen ware, Arita type)",
          "alt_text": "Small porcelain dish with a scalloped brown rim and a blue-painted bird among plum blossoms",
          "image_url": "https://images.metmuseum.org/CRDImages/as/mobile-large/DP234645.jpg",
          "highlight": false,
          "score": 0.48,
          "tag": "affinity"
        }
      ],
      "lat": 40.780285554,
      "lng": -73.962667633,
      "neighbors": [
        225,
        229,
        231
      ]
    },
    {
      "gallery": 229,
      "name": "The Infinite Artistry of Japanese Ceramics",
      "region": "japanese",
      "is_target": true,
      "time_estimate_min": 5,
      "object_count": 26,
      "featured_artworks": [
        {
          "object_id": 63648,
          "title": "Ishizara with Warbler on a Flowering Plum Branch",
          "culture": "Japan",
          "date": "early 19th century",
          "classification": "Ceramics",
          "medium": "Stoneware with iron brown and cobalt blue under transparent glaze (Seto ware)",
          "alt_text": "Shallow cream-colored stoneware dish featuring a blue bird perched on a flowering branch with brown line accents",
          "image_url": "https://images.metmuseum.org/CRDImages/as/mobile-large/DP-42390-001.jpg",
          "highlight": false,
          "score": 0.48,
          "tag": "affinity"
        },
        {
          "object_id": 63651,
          "title": "Ishizara with Horse and \u201cHorse-Eye\u201d Pattern",
          "culture": "Japan",
          "date": "early 19th century",
          "classification": "Ceramics",
          "medium": "Stoneware with iron brown under transparent glaze (Seto ware)",
          "alt_text": "Shallow circular stoneware dish featuring a stylized central horse and a border of six spiral patterns",
          "image_url": "https://images.metmuseum.org/CRDImages/as/mobile-large/DP-42391-001.jpg",
          "highlight": false,
          "score": 0.48,
          "tag": "stretch"
        },
        {
          "object_id": 63652,
          "title": "Ishizara with \u201cHorse-Eye\u201d Pattern",
          "culture": "Japan",
          "date": "early 19th century",
          "classification": "Ceramics",
          "medium": "Stoneware with iron brown under transparent glaze (Seto ware)",
          "alt_text": "Shallow stoneware dish with cream crackle glaze and five dark brown spiral motifs around the inner rim",
          "image_url": "https://images.metmuseum.org/CRDImages/as/mobile-large/DP-44152-001.jpg",
          "highlight": false,
          "score": 0.48,
          "tag": "wildcard"
        }
      ],
      "lat": 40.780318875,
      "lng": -73.962765805,
      "neighbors": [
        226,
        228,
        230
      ]
    },
    {
      "gallery": 226,
      "name": "The Infinite Artistry of Japanese Ceramics",
      "region": "japanese",
      "is_target": true,
      "time_estimate_min": 5,
      "object_count": 10,
      "featured_artworks": [
        {
          "object_id": 44858,
          "title": "Old Plum",
          "culture": "Japan",
          "date": "1646",
          "classification": "Paintings",
          "medium": "Four sliding-door panels (fusuma); ink, color, gold, and gold leaf on paper \r\n",
          "alt_text": "Four horizontal sliding-door panels depicting a gnarled tree with small blossoms against a gold leaf grid",
          "image_url": "https://images.metmuseum.org/CRDImages/as/mobile-large/DT229.jpg",
          "highlight": true,
          "score": 0.58,
          "tag": "affinity"
        },
        {
          "object_id": 45258,
          "title": "Bamboo in the Four Seasons",
          "culture": "Japan",
          "date": "late 15th\u2013early 16th century",
          "classification": "Paintings",
          "medium": "Pair of six-panel screens; ink, color, and gold leaf on paper \r\n",
          "alt_text": "A six-panel horizontal screen depicting thick green bamboo stalks and brown shoots against a gold-toned background",
          "image_url": "https://images.metmuseum.org/CRDImages/as/mobile-large/DT1607.jpg",
          "highlight": false,
          "score": 0.48,
          "tag": "stretch"
        },
        {
          "object_id": 40312,
          "title": "Pair of Negoro Lacquer Candlesticks",
          "culture": "Japan",
          "date": "late 16th century",
          "classification": "Lacquer",
          "medium": "Wood with layers of black and red lacquer (Negoro ware)",
          "alt_text": "Pair of tall red and black lacquer candlesticks with bamboo-style stems and flared circular bases",
          "image_url": "https://images.metmuseum.org/CRDImages/as/mobile-large/DP356177.jpg",
          "highlight": false,
          "score": 0.48,
          "tag": "wildcard"
        }
      ],
      "lat": 40.780275745,
      "lng": -73.962848501,
      "neighbors": [
        225,
        227,
        229
      ]
    },
    {
      "gallery": 227,
      "name": "The Infinite Artistry of Japanese Ceramics",
      "region": "japanese",
      "is_target": true,
      "time_estimate_min": 5,
      "object_count": 25,
      "featured_artworks": [
        {
          "object_id": 63565,
          "title": "Jar (Tsubo) with Stylized Net Design",
          "culture": "Japan",
          "date": "ca. 1620\u201340",
          "classification": "Ceramics",
          "medium": "Porcelain with cobalt blue under transparent glaze (Hizen ware, Arita type)",
          "alt_text": "Bulbous porcelain jar with a hand-painted blue net-like pattern of overlapping U-shapes on white glaze",
          "image_url": "https://images.metmuseum.org/CRDImages/as/mobile-large/DP272543.jpg",
          "highlight": false,
          "score": 0.48,
          "tag": "affinity"
        },
        {
          "object_id": 50320,
          "title": "Small Dish (Kozara) with Flower Arrangement in a Pot",
          "culture": "Japan",
          "date": "ca. 1620\u201340",
          "classification": "Ceramics",
          "medium": "Porcelain with cobalt blue under transparent glaze (Hizen ware, Arita type)",
          "alt_text": "Circular porcelain dish featuring a blue underglaze depiction of flowers in a low, footed pot",
          "image_url": "https://images.metmuseum.org/CRDImages/as/mobile-large/DP-42385-001.jpg",
          "highlight": false,
          "score": 0.48,
          "tag": "stretch"
        },
        {
          "object_id": 50328,
          "title": "Sake Bottle (Tokkuri) with Flowers and Grasses",
          "culture": "Japan",
          "date": "early 18th century",
          "classification": "Ceramics",
          "medium": "Porcelain with cobalt blue under transparent glaze (Hizen ware, Arita type)",
          "alt_text": "White porcelain sake bottle with a long neck and pale blue floral and grass motifs",
          "image_url": "https://images.metmuseum.org/CRDImages/as/mobile-large/DP229722.jpg",
          "highlight": false,
          "score": 0.48,
          "tag": "wildcard"
        }
      ],
      "lat": 40.7803892,
      "lng": -73.962980721,
      "neighbors": [
        226,
        228
      ]
    },
    {
      "gallery": 226,
      "name": "The Infinite Artistry of Japanese Ceramics",
      "region": "japanese",
      "is_target": true,
      "time_estimate_min": 1,
      "object_count": 10,
      "featured_artworks": [],
      "lat": 40.780275745,
      "lng": -73.962848501,
      "neighbors": [
        225,
        227,
        229
      ]
    },
    {
      "gallery": 225,
      "name": "The Infinite Artistry of Japanese Ceramics",
      "region": "japanese",
      "is_target": false,
      "time_estimate_min": 2,
      "object_count": 20,
      "featured_artworks": [
        {
          "object_id": 50709,
          "title": "Jar with loop handles",
          "culture": "China",
          "date": "7th century",
          "classification": "Ceramics",
          "medium": "Stoneware with olive celadon glaze",
          "alt_text": "Stout olive-green stoneware jar with a wide mouth and two small vertical loop handles on its shoulder",
          "image_url": "https://images.metmuseum.org/CRDImages/as/mobile-large/1977_449_10.jpg",
          "highlight": false,
          "score": 0.48,
          "tag": "affinity"
        }
      ],
      "lat": 40.780222019,
      "lng": -73.962713964,
      "neighbors": [
        224,
        226,
        230
      ]
    },
    {
      "gallery": 224,
      "name": "The Infinite Artistry of Japanese Ceramics",
      "region": "japanese",
      "is_target": false,
      "time_estimate_min": 2,
      "object_count": 25,
      "featured_artworks": [
        {
          "object_id": 76084,
          "title": "The Bodhisattva Jiz\u014d",
          "culture": "Japan",
          "date": "1291",
          "classification": "Sculpture",
          "medium": "Japanese cypress wood (hinoki) with polychrome pigments, gold paint (kindei), cut gold leaf (kirikane), and rock-crystal eyes",
          "alt_text": "Wood sculpture of a standing person with a shaved head holding a staff and a small sphere",
          "image_url": "https://images.metmuseum.org/CRDImages/as/mobile-large/DP-14364-001.jpg",
          "highlight": true,
          "score": 0.58,
          "tag": "affinity"
        }
      ],
      "lat": 40.780153923,
      "lng": -73.962598275,
      "neighbors": [
        223,
        225,
        231
      ]
    },
    {
      "gallery": 223,
      "name": "The Infinite Artistry of Japanese Ceramics",
      "region": "japanese",
      "is_target": true,
      "time_estimate_min": 5,
      "object_count": 25,
      "featured_artworks": [
        {
          "object_id": 50342,
          "title": "Small Dish (Kozara) with Three Jars",
          "culture": "Japan",
          "date": "1680\u201390s",
          "classification": "Ceramics",
          "medium": "Porcelain with cobalt blue under transparent glaze and polychrome enamels over the glaze (Hizen ware, Nabeshima type)",
          "alt_text": "Circular porcelain dish featuring three decorated jars with geometric, crackled, and floral patterns on a blue ground",
          "image_url": "https://images.metmuseum.org/CRDImages/as/mobile-large/DP222421.jpg",
          "highlight": true,
          "score": 0.58,
          "tag": "affinity"
        },
        {
          "object_id": 63530,
          "title": "Dish with Assorted Treasures Floating on Waves",
          "culture": "Japan",
          "date": "late 17th\u2013early 18th century",
          "classification": "Ceramics",
          "medium": "Porcelain with cobalt blue under transparent glaze (Hizen ware, Nabeshima type)",
          "alt_text": "Circular porcelain dish with blue underglaze designs of various objects floating on a field of waves",
          "image_url": "https://images.metmuseum.org/CRDImages/as/mobile-large/66_155_3_O1.jpg",
          "highlight": false,
          "score": 0.48,
          "tag": "stretch"
        },
        {
          "object_id": 53162,
          "title": "Tobatsu Bishamonten",
          "culture": "Japan",
          "date": "late 10th\u2013early 11th century",
          "classification": "Sculpture",
          "medium": "Zelkova wood with traces of color",
          "alt_text": "Wood sculpture of an armored figure standing on the shoulders of three smaller humanoid figures",
          "image_url": "https://images.metmuseum.org/CRDImages/as/mobile-large/DP-27915-006.jpg",
          "highlight": false,
          "score": 0.48,
          "tag": "wildcard"
        }
      ],
      "lat": 40.780106867,
      "lng": -73.962499034,
      "neighbors": [
        224,
        232
      ]
    },
    {
      "gallery": 232,
      "name": "The Infinite Artistry of Japanese Ceramics",
      "region": "japanese",
      "is_target": false,
      "time_estimate_min": 1,
      "object_count": 7,
      "featured_artworks": [],
      "lat": 40.780169066,
      "lng": -73.962431458,
      "neighbors": [
        210,
        223,
        231
      ]
    },
    {
      "gallery": 210,
      "name": " Chinese Painting and Calligraphy: Selections from the Collection",
      "region": "chinese_painting",
      "is_target": true,
      "time_estimate_min": 1,
      "object_count": 28,
      "featured_artworks": [],
      "lat": 40.780212407,
      "lng": -73.962252558,
      "neighbors": [
        211,
        217,
        232
      ]
    },
    {
      "gallery": 217,
      "name": "Chinese Courtyard in the Style of the Ming Dynasty",
      "region": "chinese_painting",
      "is_target": false,
      "time_estimate_min": 1,
      "object_count": 0,
      "featured_artworks": [],
      "lat": 40.780140228,
      "lng": -73.962198618,
      "neighbors": [
        210,
        216,
        218
      ]
    },
    {
      "gallery": 218,
      "name": "Chinese Courtyard in the Style of the Ming Dynasty",
      "region": "chinese_painting",
      "is_target": true,
      "time_estimate_min": 5,
      "object_count": 28,
      "featured_artworks": [
        {
          "object_id": 65006,
          "title": "Daoist deity Zhenwu with two attendants",
          "culture": "China",
          "date": "17th century",
          "classification": "Ceramics",
          "medium": "Porcelain with turquoise and aubergine glazes (Jingdezhen ware)",
          "alt_text": "A turquoise and purple glazed ceramic sculpture of a large seated person and two standing attendants",
          "image_url": "https://images.metmuseum.org/CRDImages/as/mobile-large/DP-18155-001.jpg",
          "highlight": false,
          "score": 0.48,
          "tag": "affinity"
        },
        {
          "object_id": 42156,
          "title": "Wall panel with stone paintings",
          "culture": "China",
          "date": "19th century",
          "classification": "Furniture",
          "medium": "Hardwood with veined marble and brass fittings",
          "alt_text": "Four vertical dark wood panels featuring circular and rectangular stone inlays with veined landscape-like patterns",
          "image_url": "https://images.metmuseum.org/CRDImages/as/mobile-large/1995_418a-d.jpg",
          "highlight": false,
          "score": 0.48,
          "tag": "stretch"
        },
        {
          "object_id": 42739,
          "title": "Water Buffalo",
          "culture": "China",
          "date": "18th century",
          "classification": "Jade",
          "medium": "Jade (nephrite)",
          "alt_text": "Reclining water buffalo sculpture carved from dark green jade with large curved horns and tucked limbs",
          "image_url": "https://images.metmuseum.org/CRDImages/as/mobile-large/DP-19133-001.jpg",
          "highlight": false,
          "score": 0.48,
          "tag": "wildcard"
        }
      ],
      "lat": 40.780257355,
      "lng": -73.962076788,
      "neighbors": [
        217,
        213
      ]
    },
    {
      "gallery": 217,
      "name": "Chinese Courtyard in the Style of the Ming Dynasty",
      "region": "chinese_painting",
      "is_target": false,
      "time_estimate_min": 1,
      "object_count": 0,
      "featured_artworks": [],
      "lat": 40.780140228,
      "lng": -73.962198618,
      "neighbors": [
        210,
        216,
        218
      ]
    },
    {
      "gallery": 216,
      "name": " Chinese Painting and Calligraphy: Selections from the Collection",
      "region": "chinese_painting",
      "is_target": true,
      "time_estimate_min": 1,
      "object_count": 2,
      "featured_artworks": [],
      "lat": 40.780057202,
      "lng": -73.962077937,
      "neighbors": [
        215,
        217,
        244,
        253
      ]
    },
    {
      "gallery": 215,
      "name": " Chinese Painting and Calligraphy: Selections from the Collection",
      "region": "chinese_painting",
      "is_target": true,
      "time_estimate_min": 5,
      "object_count": 4,
      "featured_artworks": [
        {
          "object_id": 910543,
          "title": "Woman at her dressing table",
          "culture": "China",
          "date": "early 18th century",
          "classification": "Paintings",
          "medium": "Hanging scroll; ink and color on silk",
          "alt_text": "Person in traditional dress sitting at a table while another stands behind and arranges their hair",
          "image_url": "https://images.metmuseum.org/CRDImages/as/mobile-large/DP-34237-002.jpg",
          "highlight": true,
          "score": 0.58,
          "tag": "affinity"
        },
        {
          "object_id": 737733,
          "title": "Small portrait of Luzhu",
          "culture": "China",
          "date": "1823",
          "classification": "Paintings",
          "medium": "Hanging scroll; ink and color on paper",
          "alt_text": "Person in patterned robes on a vertical scroll surrounded by handwritten characters and red seals",
          "image_url": "https://images.metmuseum.org/CRDImages/as/mobile-large/DP-41026-002.jpg",
          "highlight": false,
          "score": 0.48,
          "tag": "stretch"
        },
        {
          "object_id": 910544,
          "title": "Beauty about to bathe",
          "culture": "China",
          "date": "18th century",
          "classification": "Paintings",
          "medium": "Hanging scroll; ink and color on silk",
          "alt_text": "Woman in a sheer robe sitting on a bench beside a large basin and flowering plant",
          "image_url": "https://images.metmuseum.org/CRDImages/as/mobile-large/DP-34238-002.jpg",
          "highlight": false,
          "score": 0.48,
          "tag": "wildcard"
        }
      ],
      "lat": 40.780148237,
      "lng": -73.962011552,
      "neighbors": [
        214,
        216,
        246
      ]
    },
    {
      "gallery": 216,
      "name": " Chinese Painting and Calligraphy: Selections from the Collection",
      "region": "chinese_painting",
      "is_target": true,
      "time_estimate_min": 1,
      "object_count": 2,
      "featured_artworks": [],
      "lat": 40.780057202,
      "lng": -73.962077937,
      "neighbors": [
        215,
        217,
        244,
        253
      ]
    },
    {
      "gallery": 244,
      "name": "Southeast Asian Art",
      "region": "southeast_asian",
      "is_target": true,
      "time_estimate_min": 1,
      "object_count": 69,
      "featured_artworks": [],
      "lat": 40.779996135,
      "lng": -73.962027516,
      "neighbors": [
        216,
        241,
        243,
        245,
        247
      ]
    },
    {
      "gallery": 241,
      "name": "Indian Medieval Sculpture Gallery",
      "region": "south_asian",
      "is_target": false,
      "time_estimate_min": 1,
      "object_count": 11,
      "featured_artworks": [],
      "lat": 40.779923533,
      "lng": -73.962067714,
      "neighbors": [
        239,
        240,
        242,
        243,
        244
      ]
    },
    {
      "gallery": 240,
      "name": "South Asian Hindu-Buddhist and Jain Sculpture",
      "region": "south_asian",
      "is_target": true,
      "time_estimate_min": 5,
      "object_count": 17,
      "featured_artworks": [
        {
          "object_id": 39325,
          "title": "Standing Parvati",
          "culture": "Indian (Tamil Nadu)",
          "date": "ca. first quarter 10th century",
          "classification": "Metalwork",
          "medium": "Copper alloy",
          "alt_text": "Standing copper alloy sculpture of a woman with a tall tiered headdress and elaborate jewelry",
          "image_url": "https://images.metmuseum.org/CRDImages/as/mobile-large/DT239.jpg",
          "highlight": true,
          "score": 0.58,
          "tag": "affinity"
        },
        {
          "object_id": 39413,
          "title": "Karaikkal Ammaiyar, Shaiva Saint",
          "culture": "India (Tamil Nadu)",
          "date": "ca. late 13th century",
          "classification": "Sculpture",
          "medium": "Copper alloy",
          "alt_text": "Seated copper alloy sculpture of a smiling person with elongated earlobes holding small cymbals on a pedestal",
          "image_url": "https://images.metmuseum.org/CRDImages/as/mobile-large/DT7391.jpg",
          "highlight": true,
          "score": 0.58,
          "tag": "stretch"
        },
        {
          "object_id": 39326,
          "title": "Standing Vishnu",
          "culture": "India (Tamil Nadu)",
          "date": "ca. third quarter 10th century",
          "classification": "Metalwork",
          "medium": "Copper alloy",
          "alt_text": "Four-armed copper alloy person standing on a tiered base with ornate headpiece and jewelry",
          "image_url": "https://images.metmuseum.org/CRDImages/as/mobile-large/DT329883.jpg",
          "highlight": true,
          "score": 0.58,
          "tag": "wildcard"
        }
      ],
      "lat": 40.779836971,
      "lng": -73.962105781,
      "neighbors": [
        239,
        241
      ]
    },
    {
      "gallery": 239,
      "name": "South Asian Hindu-Buddhist and Jain Sculpture",
      "region": "south_asian",
      "is_target": false,
      "time_estimate_min": 1,
      "object_count": 2,
      "featured_artworks": [],
      "lat": 40.779898381,
      "lng": -73.962193753,
      "neighbors": [
        209,
        238,
        240,
        241
      ]
    },
    {
      "gallery": 238,
      "name": "South Asian Hindu-Buddhist and Jain Sculpture",
      "region": "south_asian",
      "is_target": true,
      "time_estimate_min": 5,
      "object_count": 27,
      "featured_artworks": [
        {
          "object_id": 38124,
          "title": "Manjuvajra Mandala",
          "culture": "Bangladesh or India (Bengal)",
          "date": "11th century",
          "classification": "Sculpture",
          "medium": "Black stone",
          "alt_text": "A dark stone sculpture of a three-headed, six-armed person seated within an ornate architectural arch",
          "image_url": "https://images.metmuseum.org/CRDImages/as/mobile-large/DP-15581-033.jpg",
          "highlight": true,
          "score": 0.58,
          "tag": "affinity"
        },
        {
          "object_id": 39189,
          "title": "Crowned Buddha",
          "culture": "India (Bihar)",
          "date": "10th\u201311th century",
          "classification": "Sculpture",
          "medium": "Bronze inlaid with silver, lapis lazuli, and rock crystal",
          "alt_text": "Bronze sculpture of a seated person with an ornate crown and jewelry within a flame-edged arch",
          "image_url": "https://images.metmuseum.org/CRDImages/as/mobile-large/16%20NEW%20DP314094r4_61E.jpg",
          "highlight": true,
          "score": 0.58,
          "tag": "stretch"
        },
        {
          "object_id": 38559,
          "title": "The Bodhisattva Vajrapani",
          "culture": "Eastern India, Bihar, probably Nalanda",
          "date": "7th\u2013early 8th century",
          "classification": "Sculpture",
          "medium": "Sandstone",
          "alt_text": "Sandstone sculpture of a standing person with an ornate headdress and a smaller companion beside them",
          "image_url": "https://images.metmuseum.org/CRDImages/as/mobile-large/DP314122.jpg",
          "highlight": true,
          "score": 0.58,
          "tag": "wildcard"
        }
      ],
      "lat": 40.779813175,
      "lng": -73.962255887,
      "neighbors": [
        237,
        239
      ]
    },
    {
      "gallery": 237,
      "name": "South Asian Hindu-Buddhist and Jain Sculpture",
      "region": "south_asian",
      "is_target": true,
      "time_estimate_min": 5,
      "object_count": 42,
      "featured_artworks": [
        {
          "object_id": 38515,
          "title": "Vaikuntha Vishnu",
          "culture": "India (Jammu & Kashmir, ancient kingdom of Kashmir)",
          "date": "last quarter of the 8th century",
          "classification": "Sculpture",
          "medium": "Stone",
          "alt_text": "Stone sculpture of a three-headed, four-armed figure standing with smaller attendants and a circular halo",
          "image_url": "https://images.metmuseum.org/CRDImages/as/mobile-large/DT5253.jpg",
          "highlight": true,
          "score": 0.58,
          "tag": "affinity"
        },
        {
          "object_id": 39345,
          "title": "Crowned  Buddha",
          "culture": "India, Ancient kingdom of Kashmir",
          "date": "9th century",
          "classification": "Sculpture",
          "medium": "Brass",
          "alt_text": "Metal sculpture of a standing figure wearing an elaborate crown and jewelry within an almond-shaped frame",
          "image_url": "https://images.metmuseum.org/CRDImages/as/mobile-large/DT229537.jpg",
          "highlight": true,
          "score": 0.58,
          "tag": "stretch"
        },
        {
          "object_id": 39346,
          "title": "Avalokiteshvara Padmapani",
          "culture": "Pakistan (Swat Valley)",
          "date": "7th century",
          "classification": "Metalwork",
          "medium": "Bronze inlaid with silver and copper\r\n\r\n",
          "alt_text": "Bronze sculpture of a seated person with silver eyes holding a flower on a tiered lotus base",
          "image_url": "https://images.metmuseum.org/CRDImages/as/mobile-large/DP272542.jpg",
          "highlight": true,
          "score": 0.58,
          "tag": "wildcard"
        }
      ],
      "lat": 40.779760304,
      "lng": -73.962294441,
      "neighbors": [
        236,
        238
      ]
    },
    {
      "gallery": 236,
      "name": "South Asian Hindu-Buddhist and Jain Sculpture",
      "region": "south_asian",
      "is_target": false,
      "time_estimate_min": 2,
      "object_count": 26,
      "featured_artworks": [
        {
          "object_id": 38198,
          "title": "Standing Buddha Offering Protection",
          "culture": "India (Uttar Pradesh, Mathura)",
          "date": "late 5th century",
          "classification": "Sculpture",
          "medium": "Red sandstone",
          "alt_text": "Standing red stone sculpture of a person in thin draped robes with a fragmented carved backdrop",
          "image_url": "https://images.metmuseum.org/CRDImages/as/mobile-large/DT237.jpg",
          "highlight": true,
          "score": 0.58,
          "tag": "affinity"
        }
      ],
      "lat": 40.779690488,
      "lng": -73.962345353,
      "neighbors": [
        235,
        237
      ]
    },
    {
      "gallery": 235,
      "name": "South Asian Hindu-Buddhist and Jain Sculpture",
      "region": "south_asian",
      "is_target": true,
      "time_estimate_min": 5,
      "object_count": 41,
      "featured_artworks": [
        {
          "object_id": 38239,
          "title": "Drum panel with scenes of the Great Departure and Temptation of the Buddha",
          "culture": "India, Nagarjunakonda, Guntur district, Andhra Pradesh",
          "date": "first half 3rd century CE",
          "classification": "Sculpture",
          "medium": "Limestone",
          "alt_text": "Limestone relief panel with two registers of numerous people and animals separated by a floral band",
          "image_url": "https://images.metmuseum.org/CRDImages/as/mobile-large/DP-18911-001.jpg",
          "highlight": true,
          "score": 0.58,
          "tag": "affinity"
        },
        {
          "object_id": 38634,
          "title": "Crowned  Bodhisattva",
          "culture": "North India (Uttar Pradesh, Mathura)",
          "date": "3rd\u2013early 4th century",
          "classification": "Sculpture",
          "medium": "Sandstone",
          "alt_text": "A reddish-brown sandstone bust of a crowned person wearing layered beaded necklaces and heavy earrings",
          "image_url": "https://images.metmuseum.org/CRDImages/as/mobile-large/DP701395.jpg",
          "highlight": true,
          "score": 0.58,
          "tag": "stretch"
        },
        {
          "object_id": 38648,
          "title": "Torso of a Bodhisattva",
          "culture": "Pakistan (ancient region of Gandhara, mondern Peshawar region)",
          "date": "ca. 5th century",
          "classification": "Sculpture",
          "medium": "Schist",
          "alt_text": "Fragmentary stone sculpture of a muscular human torso wearing elaborate necklaces and draped fabric over one shoulder",
          "image_url": "https://images.metmuseum.org/CRDImages/as/mobile-large/DT235.jpg",
          "highlight": true,
          "score": 0.58,
          "tag": "wildcard"
        }
      ],
      "lat": 40.779605905,
      "lng": -73.962407032,
      "neighbors": [
        233,
        234,
        236
      ]
    },
    {
      "gallery": 233,
      "name": "Flip Sides: Seeing Korean Art Anew",
      "region": "korean",
      "is_target": true,
      "time_estimate_min": 5,
      "object_count": 42,
      "featured_artworks": [
        {
          "object_id": 39496,
          "title": "Bird-shaped vessel",
          "culture": "Korea",
          "date": "3rd century",
          "classification": "Ceramics",
          "medium": "Earthenware",
          "alt_text": "Bird-shaped earthenware vessel with a tall crest, long neck, and two circular openings on its back",
          "image_url": "https://images.metmuseum.org/CRDImages/as/mobile-large/DT4131.jpg",
          "highlight": true,
          "score": 0.58,
          "tag": "affinity"
        },
        {
          "object_id": 50325,
          "title": "Rafter finial in the shape of a dragon\u2019s head and wind chime",
          "culture": "Korea",
          "date": "10th century",
          "classification": "Sculpture",
          "medium": "Gilt bronze",
          "alt_text": "Gilt bronze rafter finial shaped like a horned creature with bulging eyes and an open mouth",
          "image_url": "https://images.metmuseum.org/CRDImages/as/mobile-large/DT4423.jpg",
          "highlight": true,
          "score": 0.58,
          "tag": "stretch"
        },
        {
          "object_id": 72485,
          "title": "Seated bodhisattva (left attendant of a triad)",
          "culture": "Korea",
          "date": "ca. mid-17th century",
          "classification": "Sculpture",
          "medium": "Gilt wood",
          "alt_text": "Gilded wood sculpture of a person seated cross-legged wearing an elaborate crown with bird motifs",
          "image_url": "https://images.metmuseum.org/CRDImages/as/mobile-large/DP358652.jpg",
          "highlight": true,
          "score": 0.58,
          "tag": "wildcard"
        }
      ],
      "lat": 40.779601942,
      "lng": -73.962554258,
      "neighbors": [
        208,
        234,
        235
      ]
    },
    {
      "gallery": 208,
      "name": "Chinese Buddhist Art ",
      "region": "chinese_buddhist",
      "is_target": false,
      "time_estimate_min": 1,
      "object_count": 20,
      "featured_artworks": [],
      "lat": 40.779721287,
      "lng": -73.962478484,
      "neighbors": [
        207,
        209,
        233
      ]
    },
    {
      "gallery": 207,
      "name": "Chinese Art: Ancient to Tang Dynasty",
      "region": "chinese_ancient",
      "is_target": true,
      "time_estimate_min": 1,
      "object_count": 247,
      "featured_artworks": [],
      "lat": 40.77945,
      "lng": -73.96285,
      "neighbors": [
        202,
        206,
        208,
        219,
        220
      ]
    },
    {
      "gallery": 219,
      "name": "Chinese Jade & Decorative Arts",
      "region": "chinese_ancient",
      "is_target": true,
      "time_estimate_min": 1,
      "object_count": 118,
      "featured_artworks": [],
      "lat": 40.77935,
      "lng": -73.96255,
      "neighbors": [
        207,
        220,
        222
      ]
    },
    {
      "gallery": 222,
      "name": "Chinese Jade Collection",
      "region": "chinese_ancient",
      "is_target": true,
      "time_estimate_min": 5,
      "object_count": 123,
      "featured_artworks": [
        {
          "object_id": 42149,
          "title": "Table screen with landscape scene",
          "culture": "China",
          "date": "18th\u201319th century",
          "classification": "Jade",
          "medium": "Jade (nephrite)",
          "alt_text": "Carved pale green jade oval screen depicting eight people, a pavilion, and a bird in a mountain landscape",
          "image_url": "https://images.metmuseum.org/CRDImages/as/mobile-large/DP278060.jpg",
          "highlight": false,
          "score": 0.48,
          "tag": "affinity"
        },
        {
          "object_id": 42153,
          "title": "Incense burner with cover",
          "culture": "China",
          "date": "18th century",
          "classification": "Jade",
          "medium": "Jade (nephrite)",
          "alt_text": "A light-toned, fluted vessel with a dome-shaped cover and two small loop handles",
          "image_url": "https://images.metmuseum.org/CRDImages/as/mobile-large/14576.jpg",
          "highlight": false,
          "score": 0.48,
          "tag": "stretch"
        },
        {
          "object_id": 42154,
          "title": "Covered box from an incense set",
          "culture": "China",
          "date": "18th century",
          "classification": "Jade",
          "medium": "Jade (nephrite)",
          "alt_text": "Round jade box with vertical ribbing, a carved geometric top, and the number 538",
          "image_url": "https://images.metmuseum.org/CRDImages/as/mobile-large/14570.jpg",
          "highlight": false,
          "score": 0.48,
          "tag": "wildcard"
        }
      ],
      "lat": 40.77935,
      "lng": -73.9624,
      "neighbors": [
        219,
        221
      ]
    }
  ],
  "total_time_estimate": 178,
  "path_coordinates": [
    {
      "gallery": 200,
      "lat": 40.779262161,
      "lng": -73.963184305
    },
    {
      "gallery": 202,
      "lat": 40.779239302,
      "lng": -73.962979541
    },
    {
      "gallery": 207,
      "lat": 40.77945,
      "lng": -73.96285
    },
    {
      "gallery": 219,
      "lat": 40.77935,
      "lng": -73.96255
    },
    {
      "gallery": 220,
      "lat": 40.7795,
      "lng": -73.9625
    },
    {
      "gallery": 207,
      "lat": 40.77945,
      "lng": -73.96285
    },
    {
      "gallery": 208,
      "lat": 40.779721287,
      "lng": -73.962478484
    },
    {
      "gallery": 209,
      "lat": 40.77985,
      "lng": -73.9624
    },
    {
      "gallery": 239,
      "lat": 40.779898381,
      "lng": -73.962193753
    },
    {
      "gallery": 241,
      "lat": 40.779923533,
      "lng": -73.962067714
    },
    {
      "gallery": 244,
      "lat": 40.779996135,
      "lng": -73.962027516
    },
    {
      "gallery": 245,
      "lat": 40.780049147,
      "lng": -73.961988858
    },
    {
      "gallery": 246,
      "lat": 40.780109477,
      "lng": -73.961944863
    },
    {
      "gallery": 248,
      "lat": 40.780137591,
      "lng": -73.96188656
    },
    {
      "gallery": 249,
      "lat": 40.780199747,
      "lng": -73.961833947
    },
    {
      "gallery": 250,
      "lat": 40.78027289,
      "lng": -73.961787896
    },
    {
      "gallery": 249,
      "lat": 40.780199747,
      "lng": -73.961833947
    },
    {
      "gallery": 248,
      "lat": 40.780137591,
      "lng": -73.96188656
    },
    {
      "gallery": 246,
      "lat": 40.780109477,
      "lng": -73.961944863
    },
    {
      "gallery": 245,
      "lat": 40.780049147,
      "lng": -73.961988858
    },
    {
      "gallery": 247,
      "lat": 40.78003077,
      "lng": -73.961922535
    },
    {
      "gallery": 252,
      "lat": 40.780052854,
      "lng": -73.96190643
    },
    {
      "gallery": 253,
      "lat": 40.780064764,
      "lng": -73.961979045
    },
    {
      "gallery": 216,
      "lat": 40.780057202,
      "lng": -73.962077937
    },
    {
      "gallery": 217,
      "lat": 40.780140228,
      "lng": -73.962198618
    },
    {
      "gallery": 210,
      "lat": 40.780212407,
      "lng": -73.962252558
    },
    {
      "gallery": 232,
      "lat": 40.780169066,
      "lng": -73.962431458
    },
    {
      "gallery": 231,
      "lat": 40.780222751,
      "lng": -73.962535596
    },
    {
      "gallery": 230,
      "lat": 40.780285554,
      "lng": -73.962667633
    },
    {
      "gallery": 229,
      "lat": 40.780318875,
      "lng": -73.962765805
    },
    {
      "gallery": 226,
      "lat": 40.780275745,
      "lng": -73.962848501
    },
    {
      "gallery": 227,
      "lat": 40.7803892,
      "lng": -73.962980721
    },
    {
      "gallery": 226,
      "lat": 40.780275745,
      "lng": -73.962848501
    },
    {
      "gallery": 225,
      "lat": 40.780222019,
      "lng": -73.962713964
    },
    {
      "gallery": 224,
      "lat": 40.780153923,
      "lng": -73.962598275
    },
    {
      "gallery": 223,
      "lat": 40.780106867,
      "lng": -73.962499034
    },
    {
      "gallery": 232,
      "lat": 40.780169066,
      "lng": -73.962431458
    },
    {
      "gallery": 210,
      "lat": 40.780212407,
      "lng": -73.962252558
    },
    {
      "gallery": 217,
      "lat": 40.780140228,
      "lng": -73.962198618
    },
    {
      "gallery": 218,
      "lat": 40.780257355,
      "lng": -73.962076788
    },
    {
      "gallery": 217,
      "lat": 40.780140228,
      "lng": -73.962198618
    },
    {
      "gallery": 216,
      "lat": 40.780057202,
      "lng": -73.962077937
    },
    {
      "gallery": 215,
      "lat": 40.780148237,
      "lng": -73.962011552
    },
    {
      "gallery": 216,
      "lat": 40.780057202,
      "lng": -73.962077937
    },
    {
      "gallery": 244,
      "lat": 40.779996135,
      "lng": -73.962027516
    },
    {
      "gallery": 241,
      "lat": 40.779923533,
      "lng": -73.962067714
    },
    {
      "gallery": 240,
      "lat": 40.779836971,
      "lng": -73.962105781
    },
    {
      "gallery": 239,
      "lat": 40.779898381,
      "lng": -73.962193753
    },
    {
      "gallery": 238,
      "lat": 40.779813175,
      "lng": -73.962255887
    },
    {
      "gallery": 237,
      "lat": 40.779760304,
      "lng": -73.962294441
    },
    {
      "gallery": 236,
      "lat": 40.779690488,
      "lng": -73.962345353
    },
    {
      "gallery": 235,
      "lat": 40.779605905,
      "lng": -73.962407032
    },
    {
      "gallery": 233,
      "lat": 40.779601942,
      "lng": -73.962554258
    },
    {
      "gallery": 208,
      "lat": 40.779721287,
      "lng": -73.962478484
    },
    {
      "gallery": 207,
      "lat": 40.77945,
      "lng": -73.96285
    },
    {
      "gallery": 219,
      "lat": 40.77935,
      "lng": -73.96255
    },
    {
      "gallery": 222,
      "lat": 40.77935,
      "lng": -73.9624
    }
  ],
  "map_bounds": {
    "north": 40.7805892,
    "south": 40.779039302,
    "east": -73.961587896,
    "west": -73.963384305
  }
}